README.md
setup.cfg
setup.py
russel_python_interface/__init__.py
russel_python_interface/basic_routines.py
russel_python_interface/benchmark.py
russel_python_interface/engine.py
russel_python_interface/methods_file.py
russel_python_interface/multi_engine_network.py
russel_python_interface/routine.py
russel_python_interface/static_vars.py
russel_python_interface/task.py
russel_python_interface/task_sets.py
russel_python_interface.egg-info/PKG-INFO
russel_python_interface.egg-info/SOURCES.txt
russel_python_interface.egg-info/dependency_links.txt
russel_python_interface.egg-info/top_level.txt
russel_python_interface/network/__init__.py
russel_python_interface/network/network_socket.py
russel_python_interface/network/network_transaction.py
test/test_engine.py
test/test_network_transaction.py
test/test_socket.py
test/test_task.py